MLScript.py
main.py
mainView.py
modelTestingView.py
myDataSetsView.py
myGesturesView.py
myModelsView.py
HandGestureRec-0.1.7.dist-info/LICENSE
HandGestureRec-0.1.7.dist-info/METADATA
HandGestureRec-0.1.7.dist-info/WHEEL
HandGestureRec-0.1.7.dist-info/entry_points.txt
HandGestureRec-0.1.7.dist-info/top_level.txt
HandGestureRec-0.1.7.dist-info/RECORD
