Metadata-Version: 2.1
Name: HandGestureRec
Version: 0.1.7
Summary: Dynamic hand gesture detection library using ML.
Classifier: License :: OSI Approved :: MIT License
Classifier: Programming Language :: Python :: 3
Classifier: Operating System :: OS Independent
License-File: LICENSE
Requires-Dist: scikit-learn
Requires-Dist: mediapipe
Requires-Dist: opencv-python
Requires-Dist: tensorflow-macos
Requires-Dist: numpy
Requires-Dist: pandas
